itsdangerous/__init__.py
itsdangerous/_json.py
itsdangerous/encoding.py
itsdangerous/exc.py
itsdangerous/jws.py
itsdangerous/py.typed
itsdangerous/serializer.py
itsdangerous/signer.py
itsdangerous/timed.py
itsdangerous/url_safe.py
itsdangerous-2.0.0.dist-info/LICENSE.rst
itsdangerous-2.0.0.dist-info/METADATA
itsdangerous-2.0.0.dist-info/WHEEL
itsdangerous-2.0.0.dist-info/top_level.txt
itsdangerous-2.0.0.dist-info/RECORD
