Metadata-Version: 2.1
Name: itsdangerous
Version: 2.0.0
Summary: Safely pass data to untrusted environments and back.
Home-page: https://palletsprojects.com/p/itsdangerous/
Author: Armin Ronacher
Author-email: armin.ronacher@active-4.com
Maintainer: Pallets
Maintainer-email: contact@palletsprojects.com
License: BSD-3-Clause
Project-URL: Donate, https://palletsprojects.com/donate
Project-URL: Documentation, https://itsdangerous.palletsprojects.com/
Project-URL: Changes, https://itsdangerous.palletsprojects.com/changes/
Project-URL: Source Code, https://github.com/pallets/itsdangerous/
Project-URL: Issue Tracker, https://github.com/pallets/itsdangerous/issues/
Project-URL: Twitter, https://twitter.com/PalletsTeam
Project-URL: Chat, https://discord.gg/pallets
Platform: UNKNOWN
Classifier: Development Status :: 5 - Production/Stable
Classifier: Intended Audience :: Developers
Classifier: License :: OSI Approved :: BSD License
Classifier: Operating System :: OS Independent
Classifier: Programming Language :: Python
Requires-Python: >=3.6
